wisent_guard/__init__.py
wisent_guard-0.5.0.dist-info/licenses/LICENSE
wisent_guard-0.5.0.dist-info/METADATA
wisent_guard-0.5.0.dist-info/WHEEL
wisent_guard-0.5.0.dist-info/top_level.txt
wisent_guard-0.5.0.dist-info/RECORD
